[
   {
    "name": "Iron Maiden",
    "origin": "England",
    "style": "Heavy Metal",
    "link": "ironmaiden.com",
    "logos": [{
      "title": "classical",
      "svg": "ironmaiden.svg",
      "class": ""
      }, {
      "title": "sliced",
      "svg": "ironmaiden-sliced.svg",
      "class": "iron-maiden--sliced"
      }, {
      "title": "classical",
      "svg": "ironmaiden.svg",
      "class": "iron-maiden--classical"
    }]
  },  {
    "name": "Metallica",
    "origin": "USA",
    "style": "Thrash Metal",
    "link": "metallica.com",
    "logos": [{
      "title": "Oficial",
      "svg": "metallica.svg",
      "class": ""
    }]
  },  {
    "name": "AC⚡DC",
    "origin": "Australian",
    "style": "Hard Rock",
    "link": "acdc.com",
    "logos": [{
      "title": "Oficial",
      "svg": "acdc-classical.svg",
      "class": "acdc--classical"
      }, {
      "title": "Oficial",
      "svg": "acdc-classical.svg",
      "class": "acdc--classical-color"
      }, {
      "title": "Oficial",
      "svg": "acdc.svg",
      "class": ""
      }, {
      "title": "stroke",
      "svg": "acdc.svg",
      "class": "acdc--stroke"
      }, {
      "title": "Inverse",
      "svg": "acdc.svg",
      "class": "acdc--inverse"
    }]
  },  {
    "name": "Rammstein",
    "origin": "Germany",
    "style": "Industrial Metal",
    "link": "rammstein.com",
    "logos": [{
      "title": "Oficial",
      "svg": "rammstein.svg",
      "class": ""
    }]
  },  {
    "name": "The Beatles",
    "origin": "England",
    "style": "Rock",
    "link": "thebeatles.com",
    "logos": [{
      "title": "Oficial",
      "svg": "beatles.svg",
      "class": ""
    }]
  },  {
    "name": "Led Zeppelin",
    "origin": "England",
    "style": "Rock",
    "link": "ledzeppelin.com",
    "logos": [{
      "title": "Oficial",
      "svg": "ledzeppelin.svg",
      "class": ""
      }, {
      "title": "Oficial",
      "svg": "ledzeppelin-serif.svg",
      "class": ""
      }, {
      "title": "First",
      "svg": "ledzeppelin-first.svg",
      "class": ""
      }, {
      "title": "First",
      "svg": "ledzeppelin-symbols.svg",
      "class": ""
      }]
    },  {
    "name": "U2",
    "origin": "Ireland",
    "style": "Rock",
    "link": "u2.com",
    "logos": [{
      "title": "360°",
      "svg": "u2-360.svg",
      "class": ""
    }]
  }
]
